heapy/__info__.py
heapy/__init__.py
heapy/auto/__init__.py
heapy/auto/baseline.py
heapy/auto/polybase.py
heapy/auto/polynomial.py
heapy/auto/ppsignal.py
heapy/data/__init__.py
heapy/data/filefinder.py
heapy/data/retrieve.py
heapy/docs/psf_model/fxt_psf.cod
heapy/docs/psf_model/fxt_psf.dat
heapy/docs/psf_model/xrt_psf.cod
heapy/geos/__init__.py
heapy/geos/geometry.py
heapy/geos/location.py
heapy/pipe/__init__.py
heapy/pipe/batpipe.py
heapy/pipe/event.py
heapy/pipe/filter.py
heapy/pipe/image.py
heapy/temp/__init__.py
heapy/temp/lag.py
heapy/temp/txx.py
heapy/util/__init__.py
heapy/util/data.py
heapy/util/file.py
heapy/util/significance.py
heapy/util/time.py
heapyx-0.1.8.dist-info/licenses/LICENSE
heapyx-0.1.8.dist-info/METADATA
heapyx-0.1.8.dist-info/WHEEL
heapyx-0.1.8.dist-info/top_level.txt
heapyx-0.1.8.dist-info/RECORD
