Metadata-Version: 2.4
Name: heapyx
Version: 0.1.8
Summary: High-energy (X-ray and gamma-ray) astronomical data analysis tools
Home-page: https://github.com/jyangch/heapy
Author: Jun Yang
Author-email: jyang@smail.nju.edu.cn
License: GPLv3
Project-URL: Source Code, https://github.com/jyangch/heapy
Classifier: Programming Language :: Python :: 3
Classifier: License :: OSI Approved :: GNU General Public License v3 (GPLv3)
Classifier: Operating System :: POSIX :: Linux
Classifier: Operating System :: MacOS
Classifier: Topic :: Scientific/Engineering :: Astronomy
Requires-Python: >=3.8
License-File: LICENSE
Requires-Dist: numpy>=1.20.4
Requires-Dist: pandas>=1.4.2
Requires-Dist: scipy>=1.8.0
Requires-Dist: astropy>=5.2.2
Requires-Dist: matplotlib>=3.2.1
Requires-Dist: tqdm>=4.64.1
Requires-Dist: plotly>=5.22.0
Requires-Dist: pybaselines>=1.1.0
Dynamic: author
Dynamic: author-email
Dynamic: classifier
Dynamic: description
Dynamic: description-content-type
Dynamic: home-page
Dynamic: license
Dynamic: license-file
Dynamic: project-url
Dynamic: requires-dist
Dynamic: requires-python
Dynamic: summary
